pica_langchain/__init__.py
pica_langchain/client.py
pica_langchain/logger.py
pica_langchain/mcp.py
pica_langchain/models.py
pica_langchain/tools.py
pica_langchain/utils.py
pica_langchain/prompts/__init__.py
pica_langchain/prompts/authkit_system.py
pica_langchain/prompts/default_system.py
pica_langchain-2.1.0.dist-info/licenses/LICENSE
tests/__init__.py
tests/test_client.py
tests/test_tools.py
pica_langchain-2.1.0.dist-info/METADATA
pica_langchain-2.1.0.dist-info/WHEEL
pica_langchain-2.1.0.dist-info/top_level.txt
pica_langchain-2.1.0.dist-info/RECORD
