Metadata-Version: 2.4
Name: pica-langchain
Version: 2.1.0
Summary: Pica LangChain SDK
Home-page: https://www.picaos.com/
Author: Pica
Author-email: support@picaos.com
Project-URL: Documentation, https://docs.picaos.com/sdk/langchain
Project-URL: Source, https://github.com/picahq/pica-langchain
Project-URL: Releases, https://github.com/picahq/pica-langchain/releases
Project-URL: Issue Tracker, https://github.com/picahq/pica-langchain/issues
Classifier: Development Status :: 3 - Alpha
Classifier: Intended Audience :: Developers
Classifier: License :: OSI Approved :: GNU General Public License v3 (GPLv3)
Classifier: Programming Language :: Python :: 3
Classifier: Programming Language :: Python :: 3.8
Classifier: Programming Language :: Python :: 3.9
Classifier: Programming Language :: Python :: 3.10
Classifier: Programming Language :: Python :: 3.11
Requires-Python: >=3.8
License-File: LICENSE
Requires-Dist: langchain<1.0.0,>=0.3.25
Requires-Dist: langchain_openai<1.0.0,>=0.3.8
Requires-Dist: pydantic<3.0.0,>=2.11.2
Requires-Dist: requests<3.0.0,>=2.32.3
Requires-Dist: requests-toolbelt>=1.0.0
Provides-Extra: dev
Requires-Dist: pytest==8.3.5; extra == "dev"
Requires-Dist: black==25.1.0; extra == "dev"
Requires-Dist: isort==6.0.1; extra == "dev"
Requires-Dist: mypy==1.15.0; extra == "dev"
Requires-Dist: mcp>=1.0.0; extra == "dev"
Requires-Dist: langchain-mcp-adapters>=0.1.0; extra == "dev"
Dynamic: author
Dynamic: author-email
Dynamic: classifier
Dynamic: description
Dynamic: description-content-type
Dynamic: home-page
Dynamic: license-file
Dynamic: project-url
Dynamic: provides-extra
Dynamic: requires-dist
Dynamic: requires-python
Dynamic: summary
